eb808/__init__.py
eb808/api.py
eb808/middleware.py
eb808/response.py
eb808-0.0.3.dist-info/METADATA
eb808-0.0.3.dist-info/WHEEL
eb808-0.0.3.dist-info/top_level.txt
eb808-0.0.3.dist-info/RECORD
