Metadata-Version: 2.1
Name: eb808
Version: 0.0.3
Summary: eb808 Python Web Framework built for learning purposes.
Author: Walrus Autotune
Author-email: walrusautotune@protonmail.com
License: MIT
Classifier: Programming Language :: Python :: 3.6
Requires-Python: >=3.6.0
Requires-Dist: Jinja2 (==3.1.2)
Requires-Dist: parse (==1.12.1)
Requires-Dist: requests (==2.28.2)
Requires-Dist: requests-wsgi-adapter (==0.4.1)
Requires-Dist: WebOb (==1.8.5)
Requires-Dist: whitenoise (==4.1.4)
Requires-Dist: twine (==4.0.1)
